py_apache_log_digest_xethhung12/__init__.py
py_apache_log_digest_xethhung12/__main__.py
py_apache_log_digest_xethhung12/_module_apache.py
py_apache_log_digest_xethhung12/_cmd/run.py
py_apache_log_digest_xethhung12/apache/__init__.py
py_apache_log_digest_xethhung12/apache/log_processor.py
py_apache_log_digest_xethhung12/bot-agent/bot_agent.py
py_apache_log_digest_xethhung12/last_read/__init__.py
py_apache_log_digest_xethhung12/last_read/_last_read.py
py_apache_log_digest_xethhung12/last_read/read.log
py_apache_log_digest_xethhung12/official_ips/bing_ips.py
py_apache_log_digest_xethhung12/official_ips/common.py
py_apache_log_digest_xethhung12/official_ips/google_ips.py
py_apache_log_digest_xethhung12/official_ips/yandex.py
py_apache_log_digest_xethhung12-0.0.3.dist-info/METADATA
py_apache_log_digest_xethhung12-0.0.3.dist-info/WHEEL
py_apache_log_digest_xethhung12-0.0.3.dist-info/licenses/LICENSE
py_apache_log_digest_xethhung12-0.0.3.dist-info/RECORD
